oshlex
